pinecone_plugins/inference/__init__.py
pinecone_plugins/inference/build_parameters_dict_for_inference.py
pinecone_plugins/inference/core/client/__init__.py
pinecone_plugins/inference/core/client/api/__init__.py
pinecone_plugins/inference/core/client/api/inference_api.py
pinecone_plugins/inference/core/client/api_client.py
pinecone_plugins/inference/core/client/apis/__init__.py
pinecone_plugins/inference/core/client/configuration.py
pinecone_plugins/inference/core/client/exceptions.py
pinecone_plugins/inference/core/client/model/__init__.py
pinecone_plugins/inference/core/client/model/document.py
pinecone_plugins/inference/core/client/model/embed_request.py
pinecone_plugins/inference/core/client/model/embed_request_inputs.py
pinecone_plugins/inference/core/client/model/embed_request_parameters.py
pinecone_plugins/inference/core/client/model/embedding.py
pinecone_plugins/inference/core/client/model/embeddings_list.py
pinecone_plugins/inference/core/client/model/embeddings_list_usage.py
pinecone_plugins/inference/core/client/model/error_response.py
pinecone_plugins/inference/core/client/model/error_response_error.py
pinecone_plugins/inference/core/client/model/inline_object.py
pinecone_plugins/inference/core/client/model/ranked_document.py
pinecone_plugins/inference/core/client/model/rerank_result.py
pinecone_plugins/inference/core/client/model/rerank_result_usage.py
pinecone_plugins/inference/core/client/model_utils.py
pinecone_plugins/inference/core/client/models/__init__.py
pinecone_plugins/inference/core/client/rest.py
pinecone_plugins/inference/inference.py
pinecone_plugins/inference/models/__init__.py
pinecone_plugins/inference/models/embeddings_list.py
pinecone_plugins/inference/models/rerank_result.py
pinecone_plugins/inference/repl_overrides.py
pinecone_plugins/inference/version.py
pinecone_plugin_inference-2.0.0.dist-info/LICENSE.txt
pinecone_plugin_inference-2.0.0.dist-info/METADATA
pinecone_plugin_inference-2.0.0.dist-info/WHEEL
pinecone_plugin_inference-2.0.0.dist-info/RECORD
