Metadata-Version: 2.1
Name: pinecone-plugin-inference
Version: 2.0.0
Summary: Embeddings plugin for Pinecone SDK
Home-page: https://www.pinecone.io
License: Apache-2.0
Author: Pinecone Systems, Inc.
Author-email: support@pinecone.io
Requires-Python: >=3.8,<4.0
Classifier: License :: OSI Approved :: Apache Software License
Classifier: Programming Language :: Python :: 3
Classifier: Programming Language :: Python :: 3.8
Classifier: Programming Language :: Python :: 3.9
Classifier: Programming Language :: Python :: 3.10
Classifier: Programming Language :: Python :: 3.11
Classifier: Programming Language :: Python :: 3.12
Classifier: Programming Language :: Python :: 3.13
Requires-Dist: pinecone-plugin-interface (>=0.0.7,<0.0.8)
Project-URL: Documentation, https://pinecone.io/docs
